mol_ga/__init__.py
mol_ga/cached_function.py
mol_ga/general_ga.py
mol_ga/mol_libraries.py
mol_ga/preconfigured_gas.py
mol_ga/sample_population.py
mol_ga/data/README.md
mol_ga/data/zinc250k.smiles
mol_ga/graph_ga/README.md
mol_ga/graph_ga/__init__.py
mol_ga/graph_ga/crossover.py
mol_ga/graph_ga/gen_candidates.py
mol_ga/graph_ga/mutate.py
mol_ga-0.2.1.dist-info/LICENSE
mol_ga-0.2.1.dist-info/METADATA
mol_ga-0.2.1.dist-info/WHEEL
mol_ga-0.2.1.dist-info/top_level.txt
mol_ga-0.2.1.dist-info/RECORD
