Metadata-Version: 2.1
Name: mol_ga
Version: 0.2.1
Summary: Simple genetic algorithms for 2D molecular design.
Author: Austin Tripp
License: MIT License
Project-URL: Homepage, https://github.com/AustinT/mol_ga
Project-URL: Repository, https://github.com/AustinT/mol_ga.git
Keywords: genetic algorithm,molecule,chemistry
Requires-Python: >=3.7
License-File: LICENSE
Requires-Dist: numpy
Requires-Dist: rdkit
Requires-Dist: joblib
Provides-Extra: dev
Requires-Dist: pytest ; extra == 'dev'
Requires-Dist: pre-commit ; extra == 'dev'
